genotype_network/__init__.py
genotype_network/protein.py
genotype_network-0.1.6.dist-info/DESCRIPTION.rst
genotype_network-0.1.6.dist-info/METADATA
genotype_network-0.1.6.dist-info/metadata.json
genotype_network-0.1.6.dist-info/RECORD
genotype_network-0.1.6.dist-info/top_level.txt
genotype_network-0.1.6.dist-info/WHEEL
