Metadata-Version: 2.0
Name: genotype-network
Version: 0.1.6
Summary: A package for constructing and analyzing protein genotype                  networks in Python.
Home-page: https://github.com/ericmjl/genotype-network
Author: Eric J. Ma
Author-email: ericmajinglong@gmail.com
License: MIT
Keywords: proteins,networks,bioinformatics
Platform: UNKNOWN
Classifier: Development Status :: 3 - Alpha
Classifier: Intended Audience :: Science/Research
Classifier: Topic :: Scientific/Engineering :: Bio-Informatics
Classifier: License :: OSI Approved :: MIT License
Classifier: Programming Language :: Python :: 3
Classifier: Programming Language :: Python :: 3.2
Classifier: Programming Language :: Python :: 3.3
Classifier: Programming Language :: Python :: 3.4
Requires-Dist: networkx
Requires-Dist: python-Levenshtein
Requires-Dist: biopython
